scikufu/__init__.py
scikufu/file/__init__.py
scikufu/file/json.py
scikufu/file/jsonl.py
scikufu/file/text.py
scikufu/parallel/__init__.py
scikufu/parallel/openai.py
scikufu/py.typed
scikufu/stats/__init__.py
scikufu/stats/ttest.py
scikufu-0.1.1.post1.dist-info/WHEEL
scikufu-0.1.1.post1.dist-info/METADATA
scikufu-0.1.1.post1.dist-info/RECORD
