Metadata-Version: 2.3
Name: scikufu
Version: 0.1.1.post1
Summary: A Python toolkit for scientific computing and data analysis, featuring parallel processing, batch OpenAI API calls, statistical analysis, and common research utilities.
Requires-Dist: diskcache>=5.6.3 ; extra == 'parallel'
Requires-Dist: tqdm>=4.67.1 ; extra == 'parallel'
Requires-Dist: openai>=2.9.0 ; extra == 'parallel-openai'
Requires-Dist: matplotlib>=3.10.7 ; extra == 'stats'
Requires-Dist: numpy>=2.3.5 ; extra == 'stats'
Requires-Dist: pandas>=2.3.3 ; extra == 'stats'
Requires-Dist: scipy>=1.16.3 ; extra == 'stats'
Requires-Python: >=3.7
Provides-Extra: parallel
Provides-Extra: parallel-openai
Provides-Extra: stats
